zgit/__init__.py
zgit/gc/__init__.py
zgit/gc/__main__.py
zgit/gc/interact.py
zgit/git/__init__.py
zgit/git/find_git.py
zgit/git/glob.py
zgit/git/utils.py
zgit/plot/__init__.py
zgit/plot/__main__.py
zgit/plot/commit.py
zgit/plot/merge.py
zgit/plot/plot.py
zgit/sync/__init__.py
zgit/sync/__main__.py
zgit/sync/archive.py
zgit/sync/sync.py
zgit/sync/updater.py
zgit-1.0.2.dist-info/entry_points.txt
zgit-1.0.2.dist-info/LICENSE
zgit-1.0.2.dist-info/WHEEL
zgit-1.0.2.dist-info/METADATA
zgit-1.0.2.dist-info/RECORD
